dendromatics/__about__.py
dendromatics/__init__.py
dendromatics/draw.py
dendromatics/ground.py
dendromatics/individualize.py
dendromatics/sections.py
dendromatics/stripe.py
dendromatics/primitives/__init__.py
dendromatics/primitives/clustering.py
dendromatics/primitives/voxel.py
dendromatics-0.7.0.dist-info/METADATA
dendromatics-0.7.0.dist-info/WHEEL
dendromatics-0.7.0.dist-info/licenses/LICENSE
dendromatics-0.7.0.dist-info/RECORD
