Metadata-Version: 2.4
Name: dendromatics
Version: 0.7.0
Summary: Automatic dendrometry and forest inventory for terrestrial point clouds
Project-URL: Source, https://github.com/3DFin/dendromatics
Project-URL: Documentation, https://dendromatics.readthedocs.io/en/latest/
Project-URL: Issues, https://github.com/3DFin/dendromatics/issues
Author-email: Carlos Cabo <carloscabo@uniovi.es>, Diego Laino <diegolainor@gmail.com>
License-Expression: GPL-3.0-or-later
License-File: LICENSE
Keywords: forestry,lidar,tls
Classifier: Intended Audience :: Science/Research
Classifier: Programming Language :: Python
Classifier: Programming Language :: Python :: 3.10
Classifier: Programming Language :: Python :: 3.11
Classifier: Programming Language :: Python :: 3.12
Classifier: Programming Language :: Python :: 3.13
Classifier: Programming Language :: Python :: 3.14
Classifier: Topic :: Scientific/Engineering
Classifier: Topic :: Scientific/Engineering :: GIS
Requires-Python: <3.15,>=3.10
Requires-Dist: csf-3dfin~=2.0.1
Requires-Dist: laspy~=2.5.4
Requires-Dist: numpy>=1.25
Requires-Dist: pgeof~=0.3.4
Requires-Dist: scikit-learn<1.8.0,>=1.6.0
Requires-Dist: scipy<1.17.0,>=1.15.0
Provides-Extra: dendroptimized
Requires-Dist: dendroptimized~=0.2.2; extra == 'dendroptimized'
Provides-Extra: docs
Requires-Dist: sphinx; extra == 'docs'
Requires-Dist: sphinx-reference-rename; extra == 'docs'
Requires-Dist: sphinx-rtd-theme; extra == 'docs'
